{
  "openapi": "3.0.0",
  "info": {
    "title": "Psychology Clinic Appointment System API",
    "description": "API for managing psychology clinic appointments and patient records",
    "version": "1.0.0"
  },
  "servers": [
    {
      "url": "http://localhost:3000",
      "description": "Development server"
    },
    {
      "url": "https://your-render-app.onrender.com",
      "description": "Production server"
    }
  ],
  "tags": [
    {
      "name": "Patients",
      "description": "Patient management endpoints"
    },
    {
      "name": "Appointments",
      "description": "Appointment management endpoints"
    }
  ],
  "paths": {
    "/patients": {
      "get": {
        "tags": ["Patients"],
        "summary": "Get all patients",
        "responses": {
          "200": {
            "description": "Successful operation",
            "content": {
              "application/json": {
                "schema": {
                  "type": "array",
                  "items": {
                    "$ref": "#/components/schemas/Patient"
                  }
                }
              }
            }
          },
          "500": {
            "description": "Internal server error"
          }
        }
      },
      "post": {
        "tags": ["Patients"],
        "summary": "Create a new patient",
        "requestBody": {
          "required": true,
          "content": {
            "application/json": {
              "schema": {
                "$ref": "#/components/schemas/PatientInput"
              }
            }
          }
        },
        "responses": {
          "201": {
            "description": "Patient created successfully",
            "content": {
              "application/json": {
                "schema": {
                  "$ref": "#/components/schemas/Patient"
                }
              }
            }
          },
          "400": {
            "description": "Invalid input"
          },
          "500": {
            "description": "Internal server error"
          }
        }
      }
    },
    "/patients/{id}": {
      "get": {
        "tags": ["Patients"],
        "summary": "Get patient by ID",
        "parameters": [
          {
            "name": "id",
            "in": "path",
            "required": true,
            "schema": {
              "type": "string"
            }
          }
        ],
        "responses": {
          "200": {
            "description": "Successful operation",
            "content": {
              "application/json": {
                "schema": {
                  "$ref": "#/components/schemas/Patient"
                }
              }
            }
          },
          "404": {
            "description": "Patient not found"
          },
          "400": {
            "description": "Invalid ID format"
          },
          "500": {
            "description": "Internal server error"
          }
        }
      },
      "put": {
        "tags": ["Patients"],
        "summary": "Update patient",
        "parameters": [
          {
            "name": "id",
            "in": "path",
            "required": true,
            "schema": {
              "type": "string"
            }
          }
        ],
        "requestBody": {
          "required": true,
          "content": {
            "application/json": {
              "schema": {
                "$ref": "#/components/schemas/PatientInput"
              }
            }
          }
        },
        "responses": {
          "200": {
            "description": "Patient updated successfully",
            "content": {
              "application/json": {
                "schema": {
                  "$ref": "#/components/schemas/Patient"
                }
              }
            }
          },
          "400": {
            "description": "Invalid input"
          },
          "404": {
            "description": "Patient not found"
          },
          "500": {
            "description": "Internal server error"
          }
        }
      },
      "delete": {
        "tags": ["Patients"],
        "summary": "Delete patient",
        "parameters": [
          {
            "name": "id",
            "in": "path",
            "required": true,
            "schema": {
              "type": "string"
            }
          }
        ],
        "responses": {
          "200": {
            "description": "Patient deleted successfully"
          },
          "404": {
            "description": "Patient not found"
          },
          "400": {
            "description": "Invalid ID format"
          },
          "500": {
            "description": "Internal server error"
          }
        }
      }
    },
    "/appointments": {
      "get": {
        "tags": ["Appointments"],
        "summary": "Get all appointments",
        "responses": {
          "200": {
            "description": "Successful operation",
            "content": {
              "application/json": {
                "schema": {
                  "type": "array",
                  "items": {
                    "$ref": "#/components/schemas/Appointment"
                  }
                }
              }
            }
          },
          "500": {
            "description": "Internal server error"
          }
        }
      },
      "post": {
        "tags": ["Appointments"],
        "summary": "Create a new appointment",
        "requestBody": {
          "required": true,
          "content": {
            "application/json": {
              "schema": {
                "$ref": "#/components/schemas/AppointmentInput"
              }
            }
          }
        },
        "responses": {
          "201": {
            "description": "Appointment created successfully",
            "content": {
              "application/json": {
                "schema": {
                  "$ref": "#/components/schemas/Appointment"
                }
              }
            }
          },
          "400": {
            "description": "Invalid input"
          },
          "404": {
            "description": "Patient not found"
          },
          "409": {
            "description": "Time slot already booked"
          },
          "500": {
            "description": "Internal server error"
          }
        }
      }
    },
    "/appointments/{id}": {
      "get": {
        "tags": ["Appointments"],
        "summary": "Get appointment by ID",
        "parameters": [
          {
            "name": "id",
            "in": "path",
            "required": true,
            "schema": {
              "type": "string"
            }
          }
        ],
        "responses": {
          "200": {
            "description": "Successful operation",
            "content": {
              "application/json": {
                "schema": {
                  "$ref": "#/components/schemas/Appointment"
                }
              }
            }
          },
          "404": {
            "description": "Appointment not found"
          },
          "400": {
            "description": "Invalid ID format"
          },
          "500": {
            "description": "Internal server error"
          }
        }
      },
      "put": {
        "tags": ["Appointments"],
        "summary": "Update appointment",
        "parameters": [
          {
            "name": "id",
            "in": "path",
            "required": true,
            "schema": {
              "type": "string"
            }
          }
        ],
        "requestBody": {
          "required": true,
          "content": {
            "application/json": {
              "schema": {
                "$ref": "#/components/schemas/AppointmentInput"
              }
            }
          }
        },
        "responses": {
          "200": {
            "description": "Appointment updated successfully",
            "content": {
              "application/json": {
                "schema": {
                  "$ref": "#/components/schemas/Appointment"
                }
              }
            }
          },
          "400": {
            "description": "Invalid input"
          },
          "404": {
            "description": "Appointment not found"
          },
          "500": {
            "description": "Internal server error"
          }
        }
      },
      "delete": {
        "tags": ["Appointments"],
        "summary": "Delete appointment",
        "parameters": [
          {
            "name": "id",
            "in": "path",
            "required": true,
            "schema": {
              "type": "string"
            }
          }
        ],
        "responses": {
          "200": {
            "description": "Appointment deleted successfully"
          },
          "404": {
            "description": "Appointment not found"
          },
          "400": {
            "description": "Invalid ID format"
          },
          "500": {
            "description": "Internal server error"
          }
        }
      }
    },
    "/appointments/patient/{patientId}": {
      "get": {
        "tags": ["Appointments"],
        "summary": "Get appointments by patient ID",
        "parameters": [
          {
            "name": "patientId",
            "in": "path",
            "required": true,
            "schema": {
              "type": "string"
            }
          }
        ],
        "responses": {
          "200": {
            "description": "Successful operation",
            "content": {
              "application/json": {
                "schema": {
                  "type": "array",
                  "items": {
                    "$ref": "#/components/schemas/Appointment"
                  }
                }
              }
            }
          },
          "400": {
            "description": "Invalid ID format"
          },
          "500": {
            "description": "Internal server error"
          }
        }
      }
    }
  },
  "components": {
    "schemas": {
      "Patient": {
        "type": "object",
        "properties": {
          "_id": {
            "type": "string"
          },
          "firstName": {
            "type": "string"
          },
          "lastName": {
            "type": "string"
          },
          "email": {
            "type": "string"
          },
          "phone": {
            "type": "string"
          },
          "dateOfBirth": {
            "type": "string",
            "format": "date"
          },
          "gender": {
            "type": "string",
            "enum": ["Male", "Female", "Other"]
          },
          "address": {
            "type": "object",
            "properties": {
              "street": {
                "type": "string"
              },
              "city": {
                "type": "string"
              },
              "state": {
                "type": "string"
              },
              "zipCode": {
                "type": "string"
              }
            }
          },
          "emergencyContact": {
            "type": "object",
            "properties": {
              "name": {
                "type": "string"
              },
              "phone": {
                "type": "string"
              },
              "relationship": {
                "type": "string"
              }
            }
          },
          "insuranceInfo": {
            "type": "object",
            "properties": {
              "provider": {
                "type": "string"
              },
              "policyNumber": {
                "type": "string"
              }
            }
          },
          "createdAt": {
            "type": "string",
            "format": "date-time"
          },
          "updatedAt": {
            "type": "string",
            "format": "date-time"
          }
        }
      },
      "PatientInput": {
        "type": "object",
        "required": ["firstName", "lastName", "email", "phone", "dateOfBirth", "gender"],
        "properties": {
          "firstName": {
            "type": "string",
            "example": "John"
          },
          "lastName": {
            "type": "string",
            "example": "Doe"
          },
          "email": {
            "type": "string",
            "format": "email",
            "example": "john.doe@example.com"
          },
          "phone": {
            "type": "string",
            "example": "+1234567890"
          },
          "dateOfBirth": {
            "type": "string",
            "format": "date",
            "example": "1990-01-01"
          },
          "gender": {
            "type": "string",
            "enum": ["Male", "Female", "Other"],
            "example": "Male"
          },
          "address": {
            "type": "object",
            "properties": {
              "street": {
                "type": "string",
                "example": "123 Main St"
              },
              "city": {
                "type": "string",
                "example": "New York"
              },
              "state": {
                "type": "string",
                "example": "NY"
              },
              "zipCode": {
                "type": "string",
                "example": "10001"
              }
            }
          },
          "emergencyContact": {
            "type": "object",
            "properties": {
              "name": {
                "type": "string",
                "example": "Jane Doe"
              },
              "phone": {
                "type": "string",
                "example": "+1987654321"
              },
              "relationship": {
                "type": "string",
                "example": "Spouse"
              }
            }
          },
          "insuranceInfo": {
            "type": "object",
            "properties": {
              "provider": {
                "type": "string",
                "example": "ABC Insurance"
              },
              "policyNumber": {
                "type": "string",
                "example": "POL123456"
              }
            }
          }
        }
      },
      "Appointment": {
        "type": "object",
        "properties": {
          "_id": {
            "type": "string"
          },
          "patientId": {
            "$ref": "#/components/schemas/Patient"
          },
          "psychologistId": {
            "type": "string"
          },
          "appointmentDate": {
            "type": "string",
            "format": "date-time"
          },
          "duration": {
            "type": "integer"
          },
          "appointmentType": {
            "type": "string",
            "enum": ["Initial Consultation", "Therapy Session", "Follow-up", "Crisis Intervention"]
          },
          "status": {
            "type": "string",
            "enum": ["Scheduled", "Completed", "Cancelled", "No-show"]
          },
          "notes": {
            "type": "string"
          },
          "symptoms": {
            "type": "array",
            "items": {
              "type": "string"
            }
          },
          "treatmentPlan": {
            "type": "object",
            "properties": {
              "diagnosis": {
                "type": "string"
              },
              "goals": {
                "type": "array",
                "items": {
                  "type": "string"
                }
              },
              "nextSteps": {
                "type": "string"
              }
            }
          },
          "createdAt": {
            "type": "string",
            "format": "date-time"
          },
          "updatedAt": {
            "type": "string",
            "format": "date-time"
          }
        }
      },
      "AppointmentInput": {
        "type": "object",
        "required": ["patientId", "psychologistId", "appointmentDate", "duration", "appointmentType"],
        "properties": {
          "patientId": {
            "type": "string",
            "example": "64f7a1b2c9d8e7f6a5b4c3d2"
          },
          "psychologistId": {
            "type": "string",
            "example": "64f7a1b2c9d8e7f6a5b4c3d3"
          },
          "appointmentDate": {
            "type": "string",
            "format": "date-time",
            "example": "2023-09-15T10:00:00Z"
          },
          "duration": {
            "type": "integer",
            "minimum": 30,
            "maximum": 120,
            "example": 60
          },
          "appointmentType": {
            "type": "string",
            "enum": ["Initial Consultation", "Therapy Session", "Follow-up", "Crisis Intervention"],
            "example": "Therapy Session"
          },
          "status": {
            "type": "string",
            "enum": ["Scheduled", "Completed", "Cancelled", "No-show"],
            "example": "Scheduled"
          },
          "notes": {
            "type": "string",
            "example": "Patient shows signs of improvement"
          },
          "symptoms": {
            "type": "array",
            "items": {
              "type": "string"
            },
            "example": ["Anxiety", "Insomnia"]
          },
          "treatmentPlan": {
            "type": "object",
            "properties": {
              "diagnosis": {
                "type": "string",
                "example": "Generalized Anxiety Disorder"
              },
              "goals": {
                "type": "array",
                "items": {
                  "type": "string"
                },
                "example": ["Reduce anxiety symptoms", "Improve sleep quality"]
              },
              "nextSteps": {
                "type": "string",
                "example": "Continue CBT sessions weekly"
              }
            }
          }
        }
      }
    }
  }
}